{
  "metadata": {
    "soundFile": "C:\\Users\\tanma\\OneDrive\\Desktop\\Git hub\\original chatbot\\ai_avatar\\backendv2\\audios\\message_0.wav",
    "duration": 3.78
  },
  "mouthCues": [
    { "start": 0.00, "end": 0.01, "value": "X" },
    { "start": 0.01, "end": 0.08, "value": "A" },
    { "start": 0.08, "end": 0.28, "value": "C" },
    { "start": 0.28, "end": 0.35, "value": "H" },
    { "start": 0.35, "end": 0.42, "value": "C" },
    { "start": 0.42, "end": 0.49, "value": "B" },
    { "start": 0.49, "end": 0.63, "value": "C" },
    { "start": 0.63, "end": 0.71, "value": "A" },
    { "start": 0.71, "end": 1.07, "value": "F" },
    { "start": 1.07, "end": 1.14, "value": "C" },
    { "start": 1.14, "end": 1.35, "value": "E" },
    { "start": 1.35, "end": 1.49, "value": "B" },
    { "start": 1.49, "end": 1.77, "value": "F" },
    { "start": 1.77, "end": 1.84, "value": "G" },
    { "start": 1.84, "end": 1.98, "value": "E" },
    { "start": 1.98, "end": 2.12, "value": "C" },
    { "start": 2.12, "end": 2.33, "value": "B" },
    { "start": 2.33, "end": 2.40, "value": "C" },
    { "start": 2.40, "end": 2.47, "value": "D" },
    { "start": 2.47, "end": 2.68, "value": "C" },
    { "start": 2.68, "end": 2.75, "value": "B" },
    { "start": 2.75, "end": 2.82, "value": "C" },
    { "start": 2.82, "end": 2.90, "value": "A" },
    { "start": 2.90, "end": 3.22, "value": "B" },
    { "start": 3.22, "end": 3.43, "value": "C" },
    { "start": 3.43, "end": 3.57, "value": "B" },
    { "start": 3.57, "end": 3.78, "value": "X" }
  ]
}
